helloworld.py
helloworld_patricklombardo-0.0.1.dist-info/LICENSE.txt
helloworld_patricklombardo-0.0.1.dist-info/METADATA
helloworld_patricklombardo-0.0.1.dist-info/WHEEL
helloworld_patricklombardo-0.0.1.dist-info/top_level.txt
helloworld_patricklombardo-0.0.1.dist-info/RECORD
